attention_echo/__init__.py
attention_echo/cache.py
attention_echo/config.py
attention_echo/utils.py
attention_echo/torch/__init__.py
attention_echo/torch/layers.py
attention_echo-0.1.0.dist-info/METADATA
attention_echo-0.1.0.dist-info/WHEEL
attention_echo-0.1.0.dist-info/RECORD
